softlakelib/__init__.py
softlakelib/ensamblePP.py
softlakelib/ensemblePP.py
softlakelib/primaryProductionModel.py
softlake-0.2.dist-info/METADATA
softlake-0.2.dist-info/WHEEL
softlake-0.2.dist-info/top_level.txt
softlake-0.2.dist-info/RECORD
