Metadata-Version: 2.1
Name: softlake
Version: 0.2
Summary: Primary Production: library to estimate primary production in lakes
Home-page: https://ist-supsi.gitlab.io/softlake/
Author: Massimiliano Cannata
Author-email: massimiliano.cannata@gmail.com
License: UNKNOWN
Platform: UNKNOWN
Classifier: Programming Language :: Python :: 3
Classifier: License :: OSI Approved :: GNU General Public License v2 or later (GPLv2+)
Classifier: Operating System :: OS Independent
Requires-Python: >=3.6
Requires-Dist: PyYAML
Requires-Dist: matplotlib
Requires-Dist: numpy
Requires-Dist: pandas
Requires-Dist: scipy
